mtds/__init__.py
mtds/common/enums.py
mtds/common/errors.py
mtds/kafka_client.py
mtds/model_client.py
mtds/mtds.py
mtds/redis_client.py
mtds/s3_client.py
mtds-0.0.14.dist-info/METADATA
mtds-0.0.14.dist-info/WHEEL
mtds-0.0.14.dist-info/RECORD
